{
"meta":{"test_sets":[],"test_metrics":[],"learn_metrics":[{"best_value":"Min","name":"RMSE"}],"launch_mode":"Train","parameters":"","iteration_count":100,"learn_sets":["learn"],"name":"experiment"},
"iterations":[
{"learn":[3897.668312],"iteration":0,"passed_time":0.107008372,"remaining_time":10.59382883},
{"learn":[3356.025199],"iteration":1,"passed_time":0.1832949065,"remaining_time":8.981450421},
{"learn":[2944.314476],"iteration":2,"passed_time":0.2942799188,"remaining_time":9.515050707},
{"learn":[2628.498563],"iteration":3,"passed_time":0.3815695468,"remaining_time":9.157669124},
{"learn":[2386.79976],"iteration":4,"passed_time":0.459424696,"remaining_time":8.729069223},
{"learn":[2211.753785],"iteration":5,"passed_time":0.5336137445,"remaining_time":8.359948663},
{"learn":[2076.247022],"iteration":6,"passed_time":0.6079860417,"remaining_time":8.07752884},
{"learn":[1983.714212],"iteration":7,"passed_time":0.6788741538,"remaining_time":7.807052769},
{"learn":[1908.176042],"iteration":8,"passed_time":0.7573100074,"remaining_time":7.657245631},
{"learn":[1853.445438],"iteration":9,"passed_time":0.8288336153,"remaining_time":7.459502538},
{"learn":[1810.592623],"iteration":10,"passed_time":0.9231399467,"remaining_time":7.469041387},
{"learn":[1774.007483],"iteration":11,"passed_time":1.000576474,"remaining_time":7.337560807},
{"learn":[1747.262826],"iteration":12,"passed_time":1.076744426,"remaining_time":7.205905002},
{"learn":[1725.618839],"iteration":13,"passed_time":1.151379721,"remaining_time":7.072761144},
{"learn":[1704.836475],"iteration":14,"passed_time":1.224611609,"remaining_time":6.939465786},
{"learn":[1689.985434],"iteration":15,"passed_time":1.2987972,"remaining_time":6.818685298},
{"learn":[1674.359143],"iteration":16,"passed_time":1.375257691,"remaining_time":6.714493434},
{"learn":[1662.89033],"iteration":17,"passed_time":1.448059374,"remaining_time":6.596714926},
{"learn":[1651.336906],"iteration":18,"passed_time":1.519042652,"remaining_time":6.475918675},
{"learn":[1643.17332],"iteration":19,"passed_time":1.593688864,"remaining_time":6.374755457},
{"learn":[1636.719542],"iteration":20,"passed_time":1.669643818,"remaining_time":6.281041028},
{"learn":[1625.592783],"iteration":21,"passed_time":1.745290731,"remaining_time":6.187848957},
{"learn":[1619.48492],"iteration":22,"passed_time":1.817510793,"remaining_time":6.084710046},
{"learn":[1614.407852],"iteration":23,"passed_time":1.890195435,"remaining_time":5.985618877},
{"learn":[1609.625578],"iteration":24,"passed_time":1.966691635,"remaining_time":5.900074904},
{"learn":[1603.59582],"iteration":25,"passed_time":2.042435506,"remaining_time":5.813085671},
{"learn":[1598.390747],"iteration":26,"passed_time":2.121363523,"remaining_time":5.735538415},
{"learn":[1593.793794],"iteration":27,"passed_time":2.194266955,"remaining_time":5.642400742},
{"learn":[1590.445891],"iteration":28,"passed_time":2.272670684,"remaining_time":5.564124778},
{"learn":[1583.744744],"iteration":29,"passed_time":2.347512437,"remaining_time":5.477529019},
{"learn":[1579.794721],"iteration":30,"passed_time":2.422943477,"remaining_time":5.393003222},
{"learn":[1576.181706],"iteration":31,"passed_time":2.495870409,"remaining_time":5.303724618},
{"learn":[1571.936574],"iteration":32,"passed_time":2.569718459,"remaining_time":5.217307175},
{"learn":[1568.516133],"iteration":33,"passed_time":2.648946724,"remaining_time":5.142073053},
{"learn":[1566.387735],"iteration":34,"passed_time":2.720729789,"remaining_time":5.052783894},
{"learn":[1562.125395],"iteration":35,"passed_time":2.800123719,"remaining_time":4.977997723},
{"learn":[1558.81726],"iteration":36,"passed_time":2.872671279,"remaining_time":4.89130515},
{"learn":[1553.660599],"iteration":37,"passed_time":2.950609136,"remaining_time":4.814151748},
{"learn":[1551.732678],"iteration":38,"passed_time":3.02572922,"remaining_time":4.732550831},
{"learn":[1547.434581],"iteration":39,"passed_time":3.103935033,"remaining_time":4.65590255},
{"learn":[1543.061768],"iteration":40,"passed_time":3.181765474,"remaining_time":4.578638121},
{"learn":[1538.385495],"iteration":41,"passed_time":3.255720441,"remaining_time":4.495994895},
{"learn":[1535.870867],"iteration":42,"passed_time":3.331607686,"remaining_time":4.416317166},
{"learn":[1533.948334],"iteration":43,"passed_time":3.405329738,"remaining_time":4.33405603},
{"learn":[1528.337487],"iteration":44,"passed_time":3.482067895,"remaining_time":4.25586076},
{"learn":[1524.756436],"iteration":45,"passed_time":3.560659122,"remaining_time":4.179904187},
{"learn":[1521.285423],"iteration":46,"passed_time":3.647154589,"remaining_time":4.112748792},
{"learn":[1515.650044],"iteration":47,"passed_time":3.726574228,"remaining_time":4.03712208},
{"learn":[1508.63401],"iteration":48,"passed_time":3.814856057,"remaining_time":3.970564468},
{"learn":[1504.820031],"iteration":49,"passed_time":3.895202148,"remaining_time":3.895202148},
{"learn":[1501.310708],"iteration":50,"passed_time":3.97698148,"remaining_time":3.821021422},
{"learn":[1498.801469],"iteration":51,"passed_time":4.055553499,"remaining_time":3.743587845},
{"learn":[1497.046442],"iteration":52,"passed_time":4.133171275,"remaining_time":3.665265093},
{"learn":[1493.05055],"iteration":53,"passed_time":4.212707746,"remaining_time":3.588602895},
{"learn":[1488.613194],"iteration":54,"passed_time":4.290235147,"remaining_time":3.510192393},
{"learn":[1484.631105],"iteration":55,"passed_time":4.372883973,"remaining_time":3.435837407},
{"learn":[1481.443354],"iteration":56,"passed_time":4.453177606,"remaining_time":3.359414685},
{"learn":[1479.820885],"iteration":57,"passed_time":4.531616793,"remaining_time":3.281515608},
{"learn":[1476.767282],"iteration":58,"passed_time":4.612415256,"remaining_time":3.20523772},
{"learn":[1474.324963],"iteration":59,"passed_time":4.692772513,"remaining_time":3.128515009},
{"learn":[1472.57094],"iteration":60,"passed_time":4.771650822,"remaining_time":3.050727575},
{"learn":[1470.074349],"iteration":61,"passed_time":4.861401975,"remaining_time":2.979568953},
{"learn":[1466.675915],"iteration":62,"passed_time":4.941135779,"remaining_time":2.901936886},
{"learn":[1463.714279],"iteration":63,"passed_time":5.022691862,"remaining_time":2.825264172},
{"learn":[1460.0873],"iteration":64,"passed_time":5.102769496,"remaining_time":2.747645113},
{"learn":[1458.590342],"iteration":65,"passed_time":5.193622184,"remaining_time":2.675502337},
{"learn":[1455.803083],"iteration":66,"passed_time":5.318140731,"remaining_time":2.619382748},
{"learn":[1452.989744],"iteration":67,"passed_time":5.415082211,"remaining_time":2.548273982},
{"learn":[1450.888744],"iteration":68,"passed_time":5.497643121,"remaining_time":2.469955605},
{"learn":[1448.131607],"iteration":69,"passed_time":5.581106566,"remaining_time":2.391902814},
{"learn":[1446.004281],"iteration":70,"passed_time":5.665386339,"remaining_time":2.31403104},
{"learn":[1443.990885],"iteration":71,"passed_time":5.754246582,"remaining_time":2.23776256},
{"learn":[1441.057628],"iteration":72,"passed_time":5.839675181,"remaining_time":2.159879861},
{"learn":[1438.890949],"iteration":73,"passed_time":5.920226229,"remaining_time":2.080079486},
{"learn":[1436.086761],"iteration":74,"passed_time":5.999707783,"remaining_time":1.999902594},
{"learn":[1431.635432],"iteration":75,"passed_time":6.080011791,"remaining_time":1.920003724},
{"learn":[1428.72215],"iteration":76,"passed_time":6.159902219,"remaining_time":1.839970793},
{"learn":[1426.300998],"iteration":77,"passed_time":6.242827084,"remaining_time":1.760797383},
{"learn":[1424.109369],"iteration":78,"passed_time":6.332023574,"remaining_time":1.68319614},
{"learn":[1421.892291],"iteration":79,"passed_time":6.411763503,"remaining_time":1.602940876},
{"learn":[1420.291773],"iteration":80,"passed_time":6.492349384,"remaining_time":1.522896769},
{"learn":[1416.862748],"iteration":81,"passed_time":6.571415691,"remaining_time":1.442505883},
{"learn":[1413.830034],"iteration":82,"passed_time":6.65432689,"remaining_time":1.362934423},
{"learn":[1411.527495],"iteration":83,"passed_time":6.736566469,"remaining_time":1.283155518},
{"learn":[1411.21979],"iteration":84,"passed_time":6.805598385,"remaining_time":1.20098795},
{"learn":[1408.488469],"iteration":85,"passed_time":6.891390773,"remaining_time":1.121854312},
{"learn":[1406.622042],"iteration":86,"passed_time":6.969475379,"remaining_time":1.041415861},
{"learn":[1404.696654],"iteration":87,"passed_time":7.050258883,"remaining_time":0.9613989386},
{"learn":[1402.830876],"iteration":88,"passed_time":7.131966798,"remaining_time":0.8814790425},
{"learn":[1400.603316],"iteration":89,"passed_time":7.212752886,"remaining_time":0.8014169874},
{"learn":[1399.575909],"iteration":90,"passed_time":7.253015535,"remaining_time":0.7173312068},
{"learn":[1397.44581],"iteration":91,"passed_time":7.332558423,"remaining_time":0.6376137759},
{"learn":[1395.496302],"iteration":92,"passed_time":7.411018402,"remaining_time":0.5578185894},
{"learn":[1391.929095],"iteration":93,"passed_time":7.490242917,"remaining_time":0.4781006117},
{"learn":[1390.116816],"iteration":94,"passed_time":7.569184184,"remaining_time":0.3983781149},
{"learn":[1389.534244],"iteration":95,"passed_time":7.647457497,"remaining_time":0.3186440624},
{"learn":[1387.63373],"iteration":96,"passed_time":7.727524339,"remaining_time":0.2389955981},
{"learn":[1385.175132],"iteration":97,"passed_time":7.807252393,"remaining_time":0.1593316815},
{"learn":[1382.775385],"iteration":98,"passed_time":7.886989904,"remaining_time":0.07966656469},
{"learn":[1381.698539],"iteration":99,"passed_time":7.968304572,"remaining_time":0}
]}